[
  {
    "blockId": 261,
    "page": 9,
    "text": "Exercise 9.1",
    "normalizedTitle": "Exercise 9.1",
    "level": 3,
    "confidence": 0.8300000000000001,
    "source": "pattern"
  },
  {
    "blockId": 301,
    "page": 13,
    "text": "Chapter 1",
    "normalizedTitle": "Chapter 1",
    "level": 1,
    "confidence": 0.98,
    "source": "pattern"
  },
  {
    "blockId": 302,
    "page": 13,
    "text": "Review of number concepts",
    "normalizedTitle": "Review of number concepts",
    "level": 2,
    "confidence": 0.73,
    "source": "pattern"
  },
  {
    "blockId": 355,
    "page": 15,
    "text": "1.1 Different types of numbers",
    "normalizedTitle": "1.1 Different types of numbers",
    "level": 2,
    "confidence": 0.88,
    "source": "pattern"
  },
  {
    "blockId": 376,
    "page": 16,
    "text": "Exercise 1.1",
    "normalizedTitle": "Exercise 1.1",
    "level": 3,
    "confidence": 0.8300000000000001,
    "source": "pattern"
  },
  {
    "blockId": 415,
    "page": 17,
    "text": "Exercise 1.2",
    "normalizedTitle": "Exercise 1.2",
    "level": 3,
    "confidence": 0.8300000000000001,
    "source": "pattern"
  },
  {
    "blockId": 460,
    "page": 18,
    "text": "1.2 Multiples and factors",
    "normalizedTitle": "1.2 Multiples and factors",
    "level": 2,
    "confidence": 0.88,
    "source": "pattern"
  },
  {
    "blockId": 473,
    "page": 18,
    "text": "Exercise 1.3",
    "normalizedTitle": "Exercise 1.3",
    "level": 3,
    "confidence": 0.8300000000000001,
    "source": "pattern"
  },
  {
    "blockId": 514,
    "page": 19,
    "text": "Exercise 1.4",
    "normalizedTitle": "Exercise 1.4",
    "level": 3,
    "confidence": 0.8300000000000001,
    "source": "pattern"
  },
  {
    "blockId": 547,
    "page": 20,
    "text": "Exercise 1.5",
    "normalizedTitle": "Exercise 1.5",
    "level": 3,
    "confidence": 0.8300000000000001,
    "source": "pattern"
  },
  {
    "blockId": 596,
    "page": 20,
    "text": "Exercise 1.6",
    "normalizedTitle": "Exercise 1.6",
    "level": 3,
    "confidence": 0.8300000000000001,
    "source": "pattern"
  },
  {
    "blockId": 620,
    "page": 21,
    "text": "1.3 Prime numbers",
    "normalizedTitle": "1.3 Prime numbers",
    "level": 2,
    "confidence": 0.88,
    "source": "pattern"
  },
  {
    "blockId": 662,
    "page": 23,
    "text": "Exercise 1.7",
    "normalizedTitle": "Exercise 1.7",
    "level": 3,
    "confidence": 0.8300000000000001,
    "source": "pattern"
  },
  {
    "blockId": 703,
    "page": 24,
    "text": "Exercise 1.8",
    "normalizedTitle": "Exercise 1.8",
    "level": 3,
    "confidence": 0.8300000000000001,
    "source": "pattern"
  },
  {
    "blockId": 741,
    "page": 25,
    "text": "Exercise 1.9",
    "normalizedTitle": "Exercise 1.9",
    "level": 3,
    "confidence": 0.8300000000000001,
    "source": "pattern"
  },
  {
    "blockId": 777,
    "page": 26,
    "text": "1.4 Working with directed numbers",
    "normalizedTitle": "1.4 Working with directed numbers",
    "level": 2,
    "confidence": 0.88,
    "source": "pattern"
  },
  {
    "blockId": 786,
    "page": 27,
    "text": "Exercise 1.10",
    "normalizedTitle": "Exercise 1.10",
    "level": 3,
    "confidence": 0.8300000000000001,
    "source": "pattern"
  },
  {
    "blockId": 811,
    "page": 27,
    "text": "Exercise 1.11",
    "normalizedTitle": "Exercise 1.11",
    "level": 3,
    "confidence": 0.8300000000000001,
    "source": "pattern"
  },
  {
    "blockId": 877,
    "page": 29,
    "text": "1.5 Powers, roots and laws of indices",
    "normalizedTitle": "1.5 Powers, roots and laws of indices",
    "level": 2,
    "confidence": 0.88,
    "source": "pattern"
  },
  {
    "blockId": 933,
    "page": 31,
    "text": "Exercise 1.12",
    "normalizedTitle": "Exercise 1.12",
    "level": 3,
    "confidence": 0.8300000000000001,
    "source": "pattern"
  },
  {
    "blockId": 1080,
    "page": 34,
    "text": "Exercise 1.13",
    "normalizedTitle": "Exercise 1.13",
    "level": 3,
    "confidence": 0.8300000000000001,
    "source": "pattern"
  },
  {
    "blockId": 1122,
    "page": 35,
    "text": "Exercise 1.14",
    "normalizedTitle": "Exercise 1.14",
    "level": 3,
    "confidence": 0.8300000000000001,
    "source": "pattern"
  },
  {
    "blockId": 1222,
    "page": 37,
    "text": "Exercise 1.15",
    "normalizedTitle": "Exercise 1.15",
    "level": 3,
    "confidence": 0.8300000000000001,
    "source": "pattern"
  },
  {
    "blockId": 1264,
    "page": 38,
    "text": "1.6 Order of operations",
    "normalizedTitle": "1.6 Order of operations",
    "level": 2,
    "confidence": 0.88,
    "source": "pattern"
  },
  {
    "blockId": 1304,
    "page": 39,
    "text": "Exercise 1.16",
    "normalizedTitle": "Exercise 1.16",
    "level": 3,
    "confidence": 0.8300000000000001,
    "source": "pattern"
  },
  {
    "blockId": 1417,
    "page": 41,
    "text": "Exercise 1.17",
    "normalizedTitle": "Exercise 1.17",
    "level": 3,
    "confidence": 0.8300000000000001,
    "source": "pattern"
  },
  {
    "blockId": 1506,
    "page": 43,
    "text": "1.7 Rounding and estimating",
    "normalizedTitle": "1.7 Rounding and estimating",
    "level": 2,
    "confidence": 0.88,
    "source": "pattern"
  },
  {
    "blockId": 1557,
    "page": 44,
    "text": "Exercise 1.18",
    "normalizedTitle": "Exercise 1.18",
    "level": 3,
    "confidence": 0.8300000000000001,
    "source": "pattern"
  },
  {
    "blockId": 1627,
    "page": 45,
    "text": "Exercise 1.19",
    "normalizedTitle": "Exercise 1.19",
    "level": 3,
    "confidence": 0.8300000000000001,
    "source": "pattern"
  },
  {
    "blockId": 1831,
    "page": 52,
    "text": "2.1 Using letters to represent unknown values",
    "normalizedTitle": "2.1 Using letters to represent unknown values",
    "level": 2,
    "confidence": 0.88,
    "source": "pattern"
  },
  {
    "blockId": 1896,
    "page": 54,
    "text": "Exercise 2.1",
    "normalizedTitle": "Exercise 2.1",
    "level": 3,
    "confidence": 0.8300000000000001,
    "source": "pattern"
  },
  {
    "blockId": 1948,
    "page": 55,
    "text": "2.2 Substitution",
    "normalizedTitle": "2.2 Substitution",
    "level": 2,
    "confidence": 0.88,
    "source": "pattern"
  },
  {
    "blockId": 2023,
    "page": 58,
    "text": "Exercise 2.2",
    "normalizedTitle": "Exercise 2.2",
    "level": 3,
    "confidence": 0.8300000000000001,
    "source": "pattern"
  },
  {
    "blockId": 2111,
    "page": 59,
    "text": "2.3 Simplifying expressions",
    "normalizedTitle": "2.3 Simplifying expressions",
    "level": 2,
    "confidence": 0.88,
    "source": "pattern"
  },
  {
    "blockId": 2157,
    "page": 61,
    "text": "Exercise 2.3",
    "normalizedTitle": "Exercise 2.3",
    "level": 3,
    "confidence": 0.8300000000000001,
    "source": "pattern"
  },
  {
    "blockId": 2298,
    "page": 64,
    "text": "Exercise 2.4",
    "normalizedTitle": "Exercise 2.4",
    "level": 3,
    "confidence": 0.8300000000000001,
    "source": "pattern"
  },
  {
    "blockId": 2376,
    "page": 65,
    "text": "2.4 Working with brackets",
    "normalizedTitle": "2.4 Working with brackets",
    "level": 2,
    "confidence": 0.88,
    "source": "pattern"
  },
  {
    "blockId": 2406,
    "page": 66,
    "text": "Exercise 2.5",
    "normalizedTitle": "Exercise 2.5",
    "level": 3,
    "confidence": 0.8300000000000001,
    "source": "pattern"
  },
  {
    "blockId": 2483,
    "page": 68,
    "text": "Exercise 2.6",
    "normalizedTitle": "Exercise 2.6",
    "level": 3,
    "confidence": 0.8300000000000001,
    "source": "pattern"
  },
  {
    "blockId": 2546,
    "page": 69,
    "text": "Exercise 2.7",
    "normalizedTitle": "Exercise 2.7",
    "level": 3,
    "confidence": 0.8300000000000001,
    "source": "pattern"
  },
  {
    "blockId": 2586,
    "page": 69,
    "text": "2.5 Indices",
    "normalizedTitle": "2.5 Indices",
    "level": 2,
    "confidence": 0.88,
    "source": "pattern"
  },
  {
    "blockId": 2685,
    "page": 72,
    "text": "Exercise 2.8",
    "normalizedTitle": "Exercise 2.8",
    "level": 3,
    "confidence": 0.8300000000000001,
    "source": "pattern"
  },
  {
    "blockId": 2792,
    "page": 74,
    "text": "Exercise 2.9",
    "normalizedTitle": "Exercise 2.9",
    "level": 3,
    "confidence": 0.8300000000000001,
    "source": "pattern"
  },
  {
    "blockId": 2915,
    "page": 77,
    "text": "Exercise 2.10",
    "normalizedTitle": "Exercise 2.10",
    "level": 3,
    "confidence": 0.8300000000000001,
    "source": "pattern"
  },
  {
    "blockId": 3106,
    "page": 82,
    "text": "Chapter 3",
    "normalizedTitle": "Chapter 3",
    "level": 1,
    "confidence": 0.98,
    "source": "pattern"
  },
  {
    "blockId": 3132,
    "page": 84,
    "text": "3.1 Lines and angles",
    "normalizedTitle": "3.1 Lines and angles",
    "level": 2,
    "confidence": 0.88,
    "source": "pattern"
  },
  {
    "blockId": 3208,
    "page": 89,
    "text": "Exercise 3.1",
    "normalizedTitle": "Exercise 3.1",
    "level": 3,
    "confidence": 0.8300000000000001,
    "source": "pattern"
  },
  {
    "blockId": 3262,
    "page": 91,
    "text": "Exercise 3.2",
    "normalizedTitle": "Exercise 3.2",
    "level": 3,
    "confidence": 0.8300000000000001,
    "source": "pattern"
  },
  {
    "blockId": 3332,
    "page": 94,
    "text": "Exercise 3.3",
    "normalizedTitle": "Exercise 3.3",
    "level": 3,
    "confidence": 0.8300000000000001,
    "source": "pattern"
  },
  {
    "blockId": 3405,
    "page": 96,
    "text": "Exercise 3.4",
    "normalizedTitle": "Exercise 3.4",
    "level": 3,
    "confidence": 0.8300000000000001,
    "source": "pattern"
  },
  {
    "blockId": 3434,
    "page": 98,
    "text": "3.2 Triangles",
    "normalizedTitle": "3.2 Triangles",
    "level": 2,
    "confidence": 0.88,
    "source": "pattern"
  },
  {
    "blockId": 3545,
    "page": 102,
    "text": "Exercise 3.5",
    "normalizedTitle": "Exercise 3.5",
    "level": 3,
    "confidence": 0.8300000000000001,
    "source": "pattern"
  },
  {
    "blockId": 3565,
    "page": 103,
    "text": "3.3 Quadrilaterals",
    "normalizedTitle": "3.3 Quadrilaterals",
    "level": 2,
    "confidence": 0.88,
    "source": "pattern"
  },
  {
    "blockId": 3620,
    "page": 105,
    "text": "Exercise 3.6",
    "normalizedTitle": "Exercise 3.6",
    "level": 3,
    "confidence": 0.8300000000000001,
    "source": "pattern"
  },
  {
    "blockId": 3637,
    "page": 106,
    "text": "3.4 Polygons",
    "normalizedTitle": "3.4 Polygons",
    "level": 2,
    "confidence": 0.88,
    "source": "pattern"
  },
  {
    "blockId": 3702,
    "page": 109,
    "text": "Exercise 3.7",
    "normalizedTitle": "Exercise 3.7",
    "level": 3,
    "confidence": 0.8300000000000001,
    "source": "pattern"
  },
  {
    "blockId": 3727,
    "page": 109,
    "text": "3.5 Circles",
    "normalizedTitle": "3.5 Circles",
    "level": 2,
    "confidence": 0.88,
    "source": "pattern"
  },
  {
    "blockId": 3744,
    "page": 110,
    "text": "Exercise 3.8",
    "normalizedTitle": "Exercise 3.8",
    "level": 3,
    "confidence": 0.8300000000000001,
    "source": "pattern"
  },
  {
    "blockId": 3771,
    "page": 111,
    "text": "3.6 Construction",
    "normalizedTitle": "3.6 Construction",
    "level": 2,
    "confidence": 0.88,
    "source": "pattern"
  },
  {
    "blockId": 3808,
    "page": 114,
    "text": "Exercise 3.9",
    "normalizedTitle": "Exercise 3.9",
    "level": 3,
    "confidence": 0.8300000000000001,
    "source": "pattern"
  },
  {
    "blockId": 3923,
    "page": 118,
    "text": "Chapter 4",
    "normalizedTitle": "Chapter 4",
    "level": 1,
    "confidence": 0.98,
    "source": "pattern"
  },
  {
    "blockId": 3950,
    "page": 121,
    "text": "4.1 Collecting and classifying data",
    "normalizedTitle": "4.1 Collecting and classifying data",
    "level": 2,
    "confidence": 0.88,
    "source": "pattern"
  },
  {
    "blockId": 3978,
    "page": 122,
    "text": "Exercise 4.1",
    "normalizedTitle": "Exercise 4.1",
    "level": 3,
    "confidence": 0.8300000000000001,
    "source": "pattern"
  },
  {
    "blockId": 4017,
    "page": 124,
    "text": "4.2 Organising data",
    "normalizedTitle": "4.2 Organising data",
    "level": 2,
    "confidence": 0.88,
    "source": "pattern"
  },
  {
    "blockId": 4061,
    "page": 125,
    "text": "Exercise 4.2",
    "normalizedTitle": "Exercise 4.2",
    "level": 3,
    "confidence": 0.8300000000000001,
    "source": "pattern"
  },
  {
    "blockId": 4121,
    "page": 128,
    "text": "Exercise 4.3",
    "normalizedTitle": "Exercise 4.3",
    "level": 3,
    "confidence": 0.8300000000000001,
    "source": "pattern"
  },
  {
    "blockId": 4211,
    "page": 131,
    "text": "Exercise 4.4",
    "normalizedTitle": "Exercise 4.4",
    "level": 3,
    "confidence": 0.8300000000000001,
    "source": "pattern"
  },
  {
    "blockId": 4271,
    "page": 133,
    "text": "Exercise 4.5",
    "normalizedTitle": "Exercise 4.5",
    "level": 3,
    "confidence": 0.8300000000000001,
    "source": "pattern"
  },
  {
    "blockId": 4332,
    "page": 135,
    "text": "Exercise 4.6",
    "normalizedTitle": "Exercise 4.6",
    "level": 3,
    "confidence": 0.8300000000000001,
    "source": "pattern"
  },
  {
    "blockId": 4353,
    "page": 136,
    "text": "4.3 Using charts to display data",
    "normalizedTitle": "4.3 Using charts to display data",
    "level": 2,
    "confidence": 0.88,
    "source": "pattern"
  },
  {
    "blockId": 4378,
    "page": 137,
    "text": "Exercise 4.7",
    "normalizedTitle": "Exercise 4.7",
    "level": 3,
    "confidence": 0.8300000000000001,
    "source": "pattern"
  },
  {
    "blockId": 4447,
    "page": 142,
    "text": "Exercise 4.8",
    "normalizedTitle": "Exercise 4.8",
    "level": 3,
    "confidence": 0.8300000000000001,
    "source": "pattern"
  },
  {
    "blockId": 4554,
    "page": 146,
    "text": "Exercise 4.9",
    "normalizedTitle": "Exercise 4.9",
    "level": 3,
    "confidence": 0.8300000000000001,
    "source": "pattern"
  },
  {
    "blockId": 4597,
    "page": 149,
    "text": "Exercise 4.10",
    "normalizedTitle": "Exercise 4.10",
    "level": 3,
    "confidence": 0.8300000000000001,
    "source": "pattern"
  },
  {
    "blockId": 4738,
    "page": 156,
    "text": "Unit 1 Past Paper",
    "normalizedTitle": "Unit 1 Past Paper",
    "level": 1,
    "confidence": 0.95,
    "source": "pattern"
  },
  {
    "blockId": 4804,
    "page": 159,
    "text": "Unit 1 Project",
    "normalizedTitle": "Unit 1 Project",
    "level": 1,
    "confidence": 0.98,
    "source": "pattern"
  },
  {
    "blockId": 4820,
    "page": 160,
    "text": "Chapter 5",
    "normalizedTitle": "Chapter 5",
    "level": 1,
    "confidence": 0.98,
    "source": "pattern"
  },
  {
    "blockId": 4858,
    "page": 162,
    "text": "5.1 Revisiting fractions",
    "normalizedTitle": "5.1 Revisiting fractions",
    "level": 2,
    "confidence": 0.88,
    "source": "pattern"
  },
  {
    "blockId": 4896,
    "page": 163,
    "text": "Exercise 5.1",
    "normalizedTitle": "Exercise 5.1",
    "level": 3,
    "confidence": 0.8300000000000001,
    "source": "pattern"
  },
  {
    "blockId": 4925,
    "page": 164,
    "text": "5.2 Operations on fractions",
    "normalizedTitle": "5.2 Operations on fractions",
    "level": 2,
    "confidence": 0.88,
    "source": "pattern"
  },
  {
    "blockId": 4951,
    "page": 165,
    "text": "Exercise 5.2",
    "normalizedTitle": "Exercise 5.2",
    "level": 3,
    "confidence": 0.8300000000000001,
    "source": "pattern"
  },
  {
    "blockId": 4994,
    "page": 166,
    "text": "Exercise 5.3",
    "normalizedTitle": "Exercise 5.3",
    "level": 3,
    "confidence": 0.8300000000000001,
    "source": "pattern"
  },
  {
    "blockId": 5075,
    "page": 168,
    "text": "Exercise 5.4",
    "normalizedTitle": "Exercise 5.4",
    "level": 3,
    "confidence": 0.8300000000000001,
    "source": "pattern"
  },
  {
    "blockId": 5113,
    "page": 169,
    "text": "Exercise 5.5",
    "normalizedTitle": "Exercise 5.5",
    "level": 3,
    "confidence": 0.8300000000000001,
    "source": "pattern"
  },
  {
    "blockId": 5138,
    "page": 170,
    "text": "Exercise 5.6",
    "normalizedTitle": "Exercise 5.6",
    "level": 3,
    "confidence": 0.8300000000000001,
    "source": "pattern"
  },
  {
    "blockId": 5149,
    "page": 170,
    "text": "5.3 Percentages",
    "normalizedTitle": "5.3 Percentages",
    "level": 2,
    "confidence": 0.88,
    "source": "pattern"
  },
  {
    "blockId": 5202,
    "page": 173,
    "text": "Exercise 5.7",
    "normalizedTitle": "Exercise 5.7",
    "level": 3,
    "confidence": 0.8300000000000001,
    "source": "pattern"
  },
  {
    "blockId": 5268,
    "page": 174,
    "text": "Exercise 5.8",
    "normalizedTitle": "Exercise 5.8",
    "level": 3,
    "confidence": 0.8300000000000001,
    "source": "pattern"
  },
  {
    "blockId": 5303,
    "page": 175,
    "text": "Exercise 5.9",
    "normalizedTitle": "Exercise 5.9",
    "level": 3,
    "confidence": 0.8300000000000001,
    "source": "pattern"
  },
  {
    "blockId": 5356,
    "page": 177,
    "text": "Exercise 5.10",
    "normalizedTitle": "Exercise 5.10",
    "level": 3,
    "confidence": 0.8300000000000001,
    "source": "pattern"
  },
  {
    "blockId": 5431,
    "page": 180,
    "text": "Exercise 5.11",
    "normalizedTitle": "Exercise 5.11",
    "level": 3,
    "confidence": 0.8300000000000001,
    "source": "pattern"
  },
  {
    "blockId": 5466,
    "page": 181,
    "text": "5.4 Standard form",
    "normalizedTitle": "5.4 Standard form",
    "level": 2,
    "confidence": 0.88,
    "source": "pattern"
  },
  {
    "blockId": 5509,
    "page": 183,
    "text": "Exercise 5.12",
    "normalizedTitle": "Exercise 5.12",
    "level": 3,
    "confidence": 0.8300000000000001,
    "source": "pattern"
  },
  {
    "blockId": 5566,
    "page": 184,
    "text": "Exercise 5.13",
    "normalizedTitle": "Exercise 5.13",
    "level": 3,
    "confidence": 0.8300000000000001,
    "source": "pattern"
  },
  {
    "blockId": 5641,
    "page": 187,
    "text": "Exercise 5.14",
    "normalizedTitle": "Exercise 5.14",
    "level": 3,
    "confidence": 0.8300000000000001,
    "source": "pattern"
  },
  {
    "blockId": 5768,
    "page": 191,
    "text": "Chapter 6",
    "normalizedTitle": "Chapter 6",
    "level": 1,
    "confidence": 0.98,
    "source": "pattern"
  },
  {
    "blockId": 5791,
    "page": 192,
    "text": "6.1 Solving equations",
    "normalizedTitle": "6.1 Solving equations",
    "level": 2,
    "confidence": 0.88,
    "source": "pattern"
  },
  {
    "blockId": 5915,
    "page": 196,
    "text": "Exercise 6.1",
    "normalizedTitle": "Exercise 6.1",
    "level": 3,
    "confidence": 0.8300000000000001,
    "source": "pattern"
  },
  {
    "blockId": 5976,
    "page": 197,
    "text": "6.2 Factorising algebraic expressions",
    "normalizedTitle": "6.2 Factorising algebraic expressions",
    "level": 2,
    "confidence": 0.88,
    "source": "pattern"
  },
  {
    "blockId": 6027,
    "page": 198,
    "text": "Exercise 6.2",
    "normalizedTitle": "Exercise 6.2",
    "level": 3,
    "confidence": 0.8300000000000001,
    "source": "pattern"
  },
  {
    "blockId": 6097,
    "page": 200,
    "text": "6.3 Rearranging formulae",
    "normalizedTitle": "6.3 Rearranging formulae",
    "level": 2,
    "confidence": 0.88,
    "source": "pattern"
  },
  {
    "blockId": 6134,
    "page": 201,
    "text": "Exercise 6.3",
    "normalizedTitle": "Exercise 6.3",
    "level": 3,
    "confidence": 0.8300000000000001,
    "source": "pattern"
  },
  {
    "blockId": 6217,
    "page": 205,
    "text": "Chapter 7",
    "normalizedTitle": "Chapter 7",
    "level": 1,
    "confidence": 0.98,
    "source": "pattern"
  },
  {
    "blockId": 6294,
    "page": 209,
    "text": "Exercise 7.1",
    "normalizedTitle": "Exercise 7.1",
    "level": 3,
    "confidence": 0.8300000000000001,
    "source": "pattern"
  },
  {
    "blockId": 6417,
    "page": 215,
    "text": "Exercise 7.2",
    "normalizedTitle": "Exercise 7.2",
    "level": 3,
    "confidence": 0.8300000000000001,
    "source": "pattern"
  },
  {
    "blockId": 6467,
    "page": 218,
    "text": "Exercise 7.3",
    "normalizedTitle": "Exercise 7.3",
    "level": 3,
    "confidence": 0.8300000000000001,
    "source": "pattern"
  },
  {
    "blockId": 6524,
    "page": 220,
    "text": "Exercise 7.4",
    "normalizedTitle": "Exercise 7.4",
    "level": 3,
    "confidence": 0.8300000000000001,
    "source": "pattern"
  },
  {
    "blockId": 6572,
    "page": 223,
    "text": "7.2 Three-dimensional objects",
    "normalizedTitle": "7.2 Three-dimensional objects",
    "level": 2,
    "confidence": 0.88,
    "source": "pattern"
  },
  {
    "blockId": 6583,
    "page": 224,
    "text": "Exercise 7.5",
    "normalizedTitle": "Exercise 7.5",
    "level": 3,
    "confidence": 0.8300000000000001,
    "source": "pattern"
  },
  {
    "blockId": 6603,
    "page": 225,
    "text": "7.3 Surface areas and volumes of solids",
    "normalizedTitle": "7.3 Surface areas and volumes of solids",
    "level": 2,
    "confidence": 0.88,
    "source": "pattern"
  },
  {
    "blockId": 6644,
    "page": 228,
    "text": "Exercise 7.6",
    "normalizedTitle": "Exercise 7.6",
    "level": 3,
    "confidence": 0.8300000000000001,
    "source": "pattern"
  },
  {
    "blockId": 6702,
    "page": 231,
    "text": "Exercise 7.7",
    "normalizedTitle": "Exercise 7.7",
    "level": 3,
    "confidence": 0.8300000000000001,
    "source": "pattern"
  },
  {
    "blockId": 6757,
    "page": 235,
    "text": "Chapter 1 if you need some suggestions for sentence stems to get started.",
    "normalizedTitle": "Chapter 1 if you need some suggestions for sentence stems to get started.",
    "level": 1,
    "confidence": 0.95,
    "source": "pattern"
  },
  {
    "blockId": 6815,
    "page": 239,
    "text": "Chapter 8",
    "normalizedTitle": "Chapter 8",
    "level": 1,
    "confidence": 0.98,
    "source": "pattern"
  },
  {
    "blockId": 6835,
    "page": 240,
    "text": "8.1 Understanding basic probability",
    "normalizedTitle": "8.1 Understanding basic probability",
    "level": 2,
    "confidence": 0.88,
    "source": "pattern"
  },
  {
    "blockId": 6953,
    "page": 244,
    "text": "Exercise 8.1",
    "normalizedTitle": "Exercise 8.1",
    "level": 3,
    "confidence": 0.8300000000000001,
    "source": "pattern"
  },
  {
    "blockId": 7012,
    "page": 246,
    "text": "8.2 Sample space diagrams",
    "normalizedTitle": "8.2 Sample space diagrams",
    "level": 2,
    "confidence": 0.88,
    "source": "pattern"
  },
  {
    "blockId": 7044,
    "page": 247,
    "text": "Exercise 8.2",
    "normalizedTitle": "Exercise 8.2",
    "level": 3,
    "confidence": 0.8300000000000001,
    "source": "pattern"
  },
  {
    "blockId": 8604,
    "page": 250,
    "text": "8.3 Combining independent and mutually exclusive events",
    "normalizedTitle": "8.3 Combining independent and mutually exclusive events",
    "level": 2,
    "confidence": 0.88,
    "source": "pattern"
  },
  {
    "blockId": 8677,
    "page": 253,
    "text": "Exercise 8.3",
    "normalizedTitle": "Exercise 8.3",
    "level": 3,
    "confidence": 0.8300000000000001,
    "source": "pattern"
  },
  {
    "blockId": 8796,
    "page": 257,
    "text": "Unit 2 Past Paper Questions Resource Sheet is available on Cambridge GO.",
    "normalizedTitle": "Unit 2 Past Paper Questions Resource Sheet is available on Cambridge GO.",
    "level": 1,
    "confidence": 0.95,
    "source": "pattern"
  },
  {
    "blockId": 8930,
    "page": 264,
    "text": "Chapter 9",
    "normalizedTitle": "Chapter 9",
    "level": 1,
    "confidence": 0.98,
    "source": "pattern"
  },
  {
    "blockId": 8986,
    "page": 266,
    "text": "9.1 Sequences",
    "normalizedTitle": "9.1 Sequences",
    "level": 2,
    "confidence": 0.88,
    "source": "pattern"
  },
  {
    "blockId": 9013,
    "page": 267,
    "text": "Exercise 9.1",
    "normalizedTitle": "Exercise 9.1",
    "level": 3,
    "confidence": 0.8300000000000001,
    "source": "pattern"
  },
  {
    "blockId": 9165,
    "page": 272,
    "text": "Exercise 9.2",
    "normalizedTitle": "Exercise 9.2",
    "level": 3,
    "confidence": 0.8300000000000001,
    "source": "pattern"
  },
  {
    "blockId": 9294,
    "page": 278,
    "text": "Exercise 9.3",
    "normalizedTitle": "Exercise 9.3",
    "level": 3,
    "confidence": 0.8300000000000001,
    "source": "pattern"
  },
  {
    "blockId": 9326,
    "page": 280,
    "text": "Exercise 9.4",
    "normalizedTitle": "Exercise 9.4",
    "level": 3,
    "confidence": 0.8300000000000001,
    "source": "pattern"
  },
  {
    "blockId": 9344,
    "page": 280,
    "text": "9.2 Rational and irrational numbers",
    "normalizedTitle": "9.2 Rational and irrational numbers",
    "level": 2,
    "confidence": 0.88,
    "source": "pattern"
  },
  {
    "blockId": 9359,
    "page": 281,
    "text": "Exercise 9.5",
    "normalizedTitle": "Exercise 9.5",
    "level": 3,
    "confidence": 0.8300000000000001,
    "source": "pattern"
  },
  {
    "blockId": 9449,
    "page": 283,
    "text": "Exercise 9.6",
    "normalizedTitle": "Exercise 9.6",
    "level": 3,
    "confidence": 0.8300000000000001,
    "source": "pattern"
  },
  {
    "blockId": 9507,
    "page": 284,
    "text": "9.3 Surds",
    "normalizedTitle": "9.3 Surds",
    "level": 2,
    "confidence": 0.88,
    "source": "pattern"
  },
  {
    "blockId": 9605,
    "page": 287,
    "text": "Exercise 9.7",
    "normalizedTitle": "Exercise 9.7",
    "level": 3,
    "confidence": 0.8300000000000001,
    "source": "pattern"
  },
  {
    "blockId": 9790,
    "page": 292,
    "text": "Exercise 9.8",
    "normalizedTitle": "Exercise 9.8",
    "level": 3,
    "confidence": 0.8300000000000001,
    "source": "pattern"
  },
  {
    "blockId": 9886,
    "page": 295,
    "text": "Exercise 9.9",
    "normalizedTitle": "Exercise 9.9",
    "level": 3,
    "confidence": 0.8300000000000001,
    "source": "pattern"
  },
  {
    "blockId": 9912,
    "page": 296,
    "text": "9.4 Sets",
    "normalizedTitle": "9.4 Sets",
    "level": 2,
    "confidence": 0.88,
    "source": "pattern"
  },
  {
    "blockId": 9947,
    "page": 297,
    "text": "Exercise 9.10",
    "normalizedTitle": "Exercise 9.10",
    "level": 3,
    "confidence": 0.8300000000000001,
    "source": "pattern"
  },
  {
    "blockId": 10030,
    "page": 299,
    "text": "Exercise 9.11",
    "normalizedTitle": "Exercise 9.11",
    "level": 3,
    "confidence": 0.8300000000000001,
    "source": "pattern"
  },
  {
    "blockId": 10099,
    "page": 302,
    "text": "Exercise 9.12",
    "normalizedTitle": "Exercise 9.12",
    "level": 3,
    "confidence": 0.8300000000000001,
    "source": "pattern"
  },
  {
    "blockId": 10176,
    "page": 305,
    "text": "Exercise 9.13",
    "normalizedTitle": "Exercise 9.13",
    "level": 3,
    "confidence": 0.8300000000000001,
    "source": "pattern"
  },
  {
    "blockId": 10319,
    "page": 311,
    "text": "Chapter 10",
    "normalizedTitle": "Chapter 10",
    "level": 1,
    "confidence": 0.98,
    "source": "pattern"
  },
  {
    "blockId": 10355,
    "page": 312,
    "text": "10.1 Straight line graphs",
    "normalizedTitle": "10.1 Straight line graphs",
    "level": 2,
    "confidence": 0.88,
    "source": "pattern"
  },
  {
    "blockId": 10399,
    "page": 315,
    "text": "Exercise 10.1",
    "normalizedTitle": "Exercise 10.1",
    "level": 3,
    "confidence": 0.8300000000000001,
    "source": "pattern"
  },
  {
    "blockId": 10445,
    "page": 316,
    "text": "Exercise 10.2",
    "normalizedTitle": "Exercise 10.2",
    "level": 3,
    "confidence": 0.8300000000000001,
    "source": "pattern"
  },
  {
    "blockId": 10488,
    "page": 319,
    "text": "Exercise 10.3",
    "normalizedTitle": "Exercise 10.3",
    "level": 3,
    "confidence": 0.8300000000000001,
    "source": "pattern"
  },
  {
    "blockId": 10587,
    "page": 322,
    "text": "Exercise 10.4",
    "normalizedTitle": "Exercise 10.4",
    "level": 3,
    "confidence": 0.8300000000000001,
    "source": "pattern"
  },
  {
    "blockId": 10704,
    "page": 325,
    "text": "Exercise 10.5",
    "normalizedTitle": "Exercise 10.5",
    "level": 3,
    "confidence": 0.8300000000000001,
    "source": "pattern"
  },
  {
    "blockId": 10751,
    "page": 328,
    "text": "Exercise 10.6",
    "normalizedTitle": "Exercise 10.6",
    "level": 3,
    "confidence": 0.8300000000000001,
    "source": "pattern"
  },
  {
    "blockId": 10811,
    "page": 330,
    "text": "Exercise 10.7",
    "normalizedTitle": "Exercise 10.7",
    "level": 3,
    "confidence": 0.8300000000000001,
    "source": "pattern"
  },
  {
    "blockId": 10842,
    "page": 332,
    "text": "10.2 Quadratic expressions and equations",
    "normalizedTitle": "10.2 Quadratic expressions and equations",
    "level": 2,
    "confidence": 0.88,
    "source": "pattern"
  },
  {
    "blockId": 10898,
    "page": 334,
    "text": "Exercise 10.8",
    "normalizedTitle": "Exercise 10.8",
    "level": 3,
    "confidence": 0.8300000000000001,
    "source": "pattern"
  },
  {
    "blockId": 10973,
    "page": 335,
    "text": "Exercise 10.9",
    "normalizedTitle": "Exercise 10.9",
    "level": 3,
    "confidence": 0.8300000000000001,
    "source": "pattern"
  },
  {
    "blockId": 11071,
    "page": 338,
    "text": "Exercise 10.10",
    "normalizedTitle": "Exercise 10.10",
    "level": 3,
    "confidence": 0.8300000000000001,
    "source": "pattern"
  },
  {
    "blockId": 11168,
    "page": 340,
    "text": "Exercise 10.11",
    "normalizedTitle": "Exercise 10.11",
    "level": 3,
    "confidence": 0.8300000000000001,
    "source": "pattern"
  },
  {
    "blockId": 11255,
    "page": 341,
    "text": "Exercise 10.12",
    "normalizedTitle": "Exercise 10.12",
    "level": 3,
    "confidence": 0.8300000000000001,
    "source": "pattern"
  },
  {
    "blockId": 11422,
    "page": 348,
    "text": "11.1 Pythagoras' theorem",
    "normalizedTitle": "11.1 Pythagoras' theorem",
    "level": 2,
    "confidence": 0.88,
    "source": "pattern"
  },
  {
    "blockId": 11463,
    "page": 349,
    "text": "Exercise 11.1",
    "normalizedTitle": "Exercise 11.1",
    "level": 3,
    "confidence": 0.8300000000000001,
    "source": "pattern"
  },
  {
    "blockId": 11517,
    "page": 352,
    "text": "Exercise 11.2",
    "normalizedTitle": "Exercise 11.2",
    "level": 3,
    "confidence": 0.8300000000000001,
    "source": "pattern"
  },
  {
    "blockId": 11563,
    "page": 355,
    "text": "11.2 Understanding similar triangles",
    "normalizedTitle": "11.2 Understanding similar triangles",
    "level": 2,
    "confidence": 0.88,
    "source": "pattern"
  },
  {
    "blockId": 11618,
    "page": 357,
    "text": "Exercise 11.3",
    "normalizedTitle": "Exercise 11.3",
    "level": 3,
    "confidence": 0.8300000000000001,
    "source": "pattern"
  },
  {
    "blockId": 11672,
    "page": 360,
    "text": "11.3 Understanding similar shapes",
    "normalizedTitle": "11.3 Understanding similar shapes",
    "level": 2,
    "confidence": 0.88,
    "source": "pattern"
  },
  {
    "blockId": 11688,
    "page": 360,
    "text": "Exercise 11.4",
    "normalizedTitle": "Exercise 11.4",
    "level": 3,
    "confidence": 0.8300000000000001,
    "source": "pattern"
  },
  {
    "blockId": 11780,
    "page": 364,
    "text": "Exercise 11.5",
    "normalizedTitle": "Exercise 11.5",
    "level": 3,
    "confidence": 0.8300000000000001,
    "source": "pattern"
  },
  {
    "blockId": 11851,
    "page": 368,
    "text": "Exercise 11.6",
    "normalizedTitle": "Exercise 11.6",
    "level": 3,
    "confidence": 0.8300000000000001,
    "source": "pattern"
  },
  {
    "blockId": 11906,
    "page": 371,
    "text": "11.4 Understanding congruence",
    "normalizedTitle": "11.4 Understanding congruence",
    "level": 2,
    "confidence": 0.88,
    "source": "pattern"
  },
  {
    "blockId": 11923,
    "page": 371,
    "text": "Exercise 11.7",
    "normalizedTitle": "Exercise 11.7",
    "level": 3,
    "confidence": 0.8300000000000001,
    "source": "pattern"
  },
  {
    "blockId": 12037,
    "page": 377,
    "text": "Chapter 12",
    "normalizedTitle": "Chapter 12",
    "level": 1,
    "confidence": 0.98,
    "source": "pattern"
  },
  {
    "blockId": 12064,
    "page": 378,
    "text": "12.1 Different types of average",
    "normalizedTitle": "12.1 Different types of average",
    "level": 2,
    "confidence": 0.88,
    "source": "pattern"
  },
  {
    "blockId": 12141,
    "page": 381,
    "text": "Exercise 12.1",
    "normalizedTitle": "Exercise 12.1",
    "level": 3,
    "confidence": 0.8300000000000001,
    "source": "pattern"
  },
  {
    "blockId": 12171,
    "page": 382,
    "text": "12.2 Making comparisons using averages and ranges",
    "normalizedTitle": "12.2 Making comparisons using averages and ranges",
    "level": 2,
    "confidence": 0.88,
    "source": "pattern"
  },
  {
    "blockId": 12198,
    "page": 383,
    "text": "1.1 Calculate the mean and range of these lengths:",
    "normalizedTitle": "1.1 Calculate the mean and range of these lengths:",
    "level": 2,
    "confidence": 0.85,
    "source": "pattern"
  },
  {
    "blockId": 12211,
    "page": 384,
    "text": "Exercise 12.2",
    "normalizedTitle": "Exercise 12.2",
    "level": 3,
    "confidence": 0.8300000000000001,
    "source": "pattern"
  },
  {
    "blockId": 12263,
    "page": 386,
    "text": "12.3 Calculating averages and ranges for frequency data",
    "normalizedTitle": "12.3 Calculating averages and ranges for frequency data",
    "level": 2,
    "confidence": 0.88,
    "source": "pattern"
  },
  {
    "blockId": 12326,
    "page": 389,
    "text": "Exercise 12.3",
    "normalizedTitle": "Exercise 12.3",
    "level": 3,
    "confidence": 0.8300000000000001,
    "source": "pattern"
  },
  {
    "blockId": 12384,
    "page": 391,
    "text": "12.4 Estimating the mean and finding the modal class for grouped data",
    "normalizedTitle": "12.4 Estimating the mean and finding the modal class for grouped data",
    "level": 2,
    "confidence": 0.88,
    "source": "pattern"
  },
  {
    "blockId": 12421,
    "page": 393,
    "text": "Exercise 12.4",
    "normalizedTitle": "Exercise 12.4",
    "level": 3,
    "confidence": 0.8300000000000001,
    "source": "pattern"
  },
  {
    "blockId": 12479,
    "page": 394,
    "text": "12.5 Quartiles",
    "normalizedTitle": "12.5 Quartiles",
    "level": 2,
    "confidence": 0.88,
    "source": "pattern"
  },
  {
    "blockId": 12558,
    "page": 397,
    "text": "Exercise 12.5",
    "normalizedTitle": "Exercise 12.5",
    "level": 3,
    "confidence": 0.8300000000000001,
    "source": "pattern"
  },
  {
    "blockId": 12705,
    "page": 403,
    "text": "Unit 3 Past Paper",
    "normalizedTitle": "Unit 3 Past Paper",
    "level": 1,
    "confidence": 0.95,
    "source": "pattern"
  },
  {
    "blockId": 12837,
    "page": 410,
    "text": "Unit 3 Project",
    "normalizedTitle": "Unit 3 Project",
    "level": 1,
    "confidence": 0.98,
    "source": "pattern"
  },
  {
    "blockId": 12858,
    "page": 411,
    "text": "Chapter 13",
    "normalizedTitle": "Chapter 13",
    "level": 1,
    "confidence": 0.98,
    "source": "pattern"
  },
  {
    "blockId": 12882,
    "page": 412,
    "text": "13.1 Understanding units",
    "normalizedTitle": "13.1 Understanding units",
    "level": 2,
    "confidence": 0.88,
    "source": "pattern"
  },
  {
    "blockId": 12929,
    "page": 414,
    "text": "Exercise 13.1",
    "normalizedTitle": "Exercise 13.1",
    "level": 3,
    "confidence": 0.8300000000000001,
    "source": "pattern"
  },
  {
    "blockId": 12996,
    "page": 416,
    "text": "13.2 Time",
    "normalizedTitle": "13.2 Time",
    "level": 2,
    "confidence": 0.88,
    "source": "pattern"
  },
  {
    "blockId": 13046,
    "page": 418,
    "text": "Exercise 13.2",
    "normalizedTitle": "Exercise 13.2",
    "level": 3,
    "confidence": 0.8300000000000001,
    "source": "pattern"
  },
  {
    "blockId": 13081,
    "page": 419,
    "text": "Exercise 13.3",
    "normalizedTitle": "Exercise 13.3",
    "level": 3,
    "confidence": 0.8300000000000001,
    "source": "pattern"
  },
  {
    "blockId": 13126,
    "page": 420,
    "text": "13.3 Limits of accuracy - upper and lower bounds",
    "normalizedTitle": "13.3 Limits of accuracy - upper and lower bounds",
    "level": 2,
    "confidence": 0.88,
    "source": "pattern"
  },
  {
    "blockId": 13170,
    "page": 423,
    "text": "Exercise 13.4",
    "normalizedTitle": "Exercise 13.4",
    "level": 3,
    "confidence": 0.8300000000000001,
    "source": "pattern"
  },
  {
    "blockId": 13273,
    "page": 426,
    "text": "Exercise 13.5",
    "normalizedTitle": "Exercise 13.5",
    "level": 3,
    "confidence": 0.8300000000000001,
    "source": "pattern"
  },
  {
    "blockId": 13338,
    "page": 429,
    "text": "13.4 Conversion graphs",
    "normalizedTitle": "13.4 Conversion graphs",
    "level": 2,
    "confidence": 0.88,
    "source": "pattern"
  },
  {
    "blockId": 13355,
    "page": 430,
    "text": "Exercise 13.6",
    "normalizedTitle": "Exercise 13.6",
    "level": 3,
    "confidence": 0.8300000000000001,
    "source": "pattern"
  },
  {
    "blockId": 13402,
    "page": 432,
    "text": "13.5 Exchanging currencies",
    "normalizedTitle": "13.5 Exchanging currencies",
    "level": 2,
    "confidence": 0.88,
    "source": "pattern"
  },
  {
    "blockId": 13426,
    "page": 433,
    "text": "Exercise 13.7",
    "normalizedTitle": "Exercise 13.7",
    "level": 3,
    "confidence": 0.8300000000000001,
    "source": "pattern"
  },
  {
    "blockId": 13548,
    "page": 438,
    "text": "Chapter 14",
    "normalizedTitle": "Chapter 14",
    "level": 1,
    "confidence": 0.98,
    "source": "pattern"
  },
  {
    "blockId": 13570,
    "page": 439,
    "text": "14.1 Simultaneous linear equations",
    "normalizedTitle": "14.1 Simultaneous linear equations",
    "level": 2,
    "confidence": 0.88,
    "source": "pattern"
  },
  {
    "blockId": 13613,
    "page": 441,
    "text": "Exercise 14.1",
    "normalizedTitle": "Exercise 14.1",
    "level": 3,
    "confidence": 0.8300000000000001,
    "source": "pattern"
  },
  {
    "blockId": 13816,
    "page": 448,
    "text": "Exercise 14.2",
    "normalizedTitle": "Exercise 14.2",
    "level": 3,
    "confidence": 0.8300000000000001,
    "source": "pattern"
  },
  {
    "blockId": 13928,
    "page": 451,
    "text": "14.2 Linear inequalities",
    "normalizedTitle": "14.2 Linear inequalities",
    "level": 2,
    "confidence": 0.88,
    "source": "pattern"
  },
  {
    "blockId": 13961,
    "page": 452,
    "text": "Exercise 14.3",
    "normalizedTitle": "Exercise 14.3",
    "level": 3,
    "confidence": 0.8300000000000001,
    "source": "pattern"
  },
  {
    "blockId": 14061,
    "page": 455,
    "text": "Exercise 14.4",
    "normalizedTitle": "Exercise 14.4",
    "level": 3,
    "confidence": 0.8300000000000001,
    "source": "pattern"
  },
  {
    "blockId": 14105,
    "page": 456,
    "text": "14.3 Regions in a plane",
    "normalizedTitle": "14.3 Regions in a plane",
    "level": 2,
    "confidence": 0.88,
    "source": "pattern"
  },
  {
    "blockId": 14156,
    "page": 460,
    "text": "Exercise 14.5",
    "normalizedTitle": "Exercise 14.5",
    "level": 3,
    "confidence": 0.8300000000000001,
    "source": "pattern"
  },
  {
    "blockId": 14196,
    "page": 462,
    "text": "Exercise 14.6",
    "normalizedTitle": "Exercise 14.6",
    "level": 3,
    "confidence": 0.8300000000000001,
    "source": "pattern"
  },
  {
    "blockId": 14206,
    "page": 463,
    "text": "14.4 Completing the square",
    "normalizedTitle": "14.4 Completing the square",
    "level": 2,
    "confidence": 0.88,
    "source": "pattern"
  },
  {
    "blockId": 14242,
    "page": 464,
    "text": "Exercise 14.7",
    "normalizedTitle": "Exercise 14.7",
    "level": 3,
    "confidence": 0.8300000000000001,
    "source": "pattern"
  },
  {
    "blockId": 14308,
    "page": 466,
    "text": "Exercise 14.8",
    "normalizedTitle": "Exercise 14.8",
    "level": 3,
    "confidence": 0.8300000000000001,
    "source": "pattern"
  },
  {
    "blockId": 14331,
    "page": 466,
    "text": "14.5 Quadratic formula",
    "normalizedTitle": "14.5 Quadratic formula",
    "level": 2,
    "confidence": 0.88,
    "source": "pattern"
  },
  {
    "blockId": 14381,
    "page": 469,
    "text": "Exercise 14.9",
    "normalizedTitle": "Exercise 14.9",
    "level": 3,
    "confidence": 0.8300000000000001,
    "source": "pattern"
  },
  {
    "blockId": 14445,
    "page": 470,
    "text": "14.6 Factorising quadratics where the coefficient of  $x^2$  is not 1",
    "normalizedTitle": "14.6 Factorising quadratics where the coefficient of  $x^2$  is not 1",
    "level": 2,
    "confidence": 0.88,
    "source": "pattern"
  },
  {
    "blockId": 14498,
    "page": 472,
    "text": "Exercise 14.10",
    "normalizedTitle": "Exercise 14.10",
    "level": 3,
    "confidence": 0.8300000000000001,
    "source": "pattern"
  },
  {
    "blockId": 14532,
    "page": 472,
    "text": "Exercise 14.11",
    "normalizedTitle": "Exercise 14.11",
    "level": 3,
    "confidence": 0.8300000000000001,
    "source": "pattern"
  },
  {
    "blockId": 14550,
    "page": 472,
    "text": "14.7 Algebraic fractions",
    "normalizedTitle": "14.7 Algebraic fractions",
    "level": 2,
    "confidence": 0.88,
    "source": "pattern"
  },
  {
    "blockId": 14578,
    "page": 473,
    "text": "Exercise 14.12",
    "normalizedTitle": "Exercise 14.12",
    "level": 3,
    "confidence": 0.8300000000000001,
    "source": "pattern"
  },
  {
    "blockId": 14624,
    "page": 475,
    "text": "Exercise 14.13",
    "normalizedTitle": "Exercise 14.13",
    "level": 3,
    "confidence": 0.8300000000000001,
    "source": "pattern"
  },
  {
    "blockId": 14668,
    "page": 477,
    "text": "Exercise 14.14",
    "normalizedTitle": "Exercise 14.14",
    "level": 3,
    "confidence": 0.8300000000000001,
    "source": "pattern"
  },
  {
    "blockId": 14808,
    "page": 483,
    "text": "15.1 Scale drawings",
    "normalizedTitle": "15.1 Scale drawings",
    "level": 2,
    "confidence": 0.88,
    "source": "pattern"
  },
  {
    "blockId": 14838,
    "page": 484,
    "text": "Exercise 15.1",
    "normalizedTitle": "Exercise 15.1",
    "level": 3,
    "confidence": 0.8300000000000001,
    "source": "pattern"
  },
  {
    "blockId": 14861,
    "page": 486,
    "text": "Exercise 15.2",
    "normalizedTitle": "Exercise 15.2",
    "level": 3,
    "confidence": 0.8300000000000001,
    "source": "pattern"
  },
  {
    "blockId": 14877,
    "page": 487,
    "text": "15.2 Bearings",
    "normalizedTitle": "15.2 Bearings",
    "level": 2,
    "confidence": 0.88,
    "source": "pattern"
  },
  {
    "blockId": 14908,
    "page": 488,
    "text": "Exercise 15.3",
    "normalizedTitle": "Exercise 15.3",
    "level": 3,
    "confidence": 0.8300000000000001,
    "source": "pattern"
  },
  {
    "blockId": 14946,
    "page": 490,
    "text": "15.3 Understanding the tangent, cosine and sine ratios",
    "normalizedTitle": "15.3 Understanding the tangent, cosine and sine ratios",
    "level": 2,
    "confidence": 0.88,
    "source": "pattern"
  },
  {
    "blockId": 14953,
    "page": 490,
    "text": "Exercise 15.4",
    "normalizedTitle": "Exercise 15.4",
    "level": 3,
    "confidence": 0.8300000000000001,
    "source": "pattern"
  },
  {
    "blockId": 15020,
    "page": 493,
    "text": "Exercise 15.5",
    "normalizedTitle": "Exercise 15.5",
    "level": 3,
    "confidence": 0.8300000000000001,
    "source": "pattern"
  },
  {
    "blockId": 15123,
    "page": 498,
    "text": "Exercise 15.6",
    "normalizedTitle": "Exercise 15.6",
    "level": 3,
    "confidence": 0.8300000000000001,
    "source": "pattern"
  },
  {
    "blockId": 15228,
    "page": 503,
    "text": "Exercise 15.7",
    "normalizedTitle": "Exercise 15.7",
    "level": 3,
    "confidence": 0.8300000000000001,
    "source": "pattern"
  },
  {
    "blockId": 15361,
    "page": 506,
    "text": "15.4 Exact trigonometric ratios",
    "normalizedTitle": "15.4 Exact trigonometric ratios",
    "level": 2,
    "confidence": 0.88,
    "source": "pattern"
  },
  {
    "blockId": 15414,
    "page": 509,
    "text": "Exercise 15.8",
    "normalizedTitle": "Exercise 15.8",
    "level": 3,
    "confidence": 0.8300000000000001,
    "source": "pattern"
  },
  {
    "blockId": 15427,
    "page": 510,
    "text": "15.5 Solving problems using trigonometry",
    "normalizedTitle": "15.5 Solving problems using trigonometry",
    "level": 2,
    "confidence": 0.88,
    "source": "pattern"
  },
  {
    "blockId": 15484,
    "page": 513,
    "text": "Exercise 15.9",
    "normalizedTitle": "Exercise 15.9",
    "level": 3,
    "confidence": 0.8300000000000001,
    "source": "pattern"
  },
  {
    "blockId": 15531,
    "page": 516,
    "text": "15.6 Sines, cosines and tangents of angles greater than  $90^{\\circ}$",
    "normalizedTitle": "15.6 Sines, cosines and tangents of angles greater than  $90^{\\circ}$",
    "level": 2,
    "confidence": 0.88,
    "source": "pattern"
  },
  {
    "blockId": 15622,
    "page": 520,
    "text": "Exercise 15.10",
    "normalizedTitle": "Exercise 15.10",
    "level": 3,
    "confidence": 0.8300000000000001,
    "source": "pattern"
  },
  {
    "blockId": 15665,
    "page": 521,
    "text": "15.7 The sine and cosine rules",
    "normalizedTitle": "15.7 The sine and cosine rules",
    "level": 2,
    "confidence": 0.88,
    "source": "pattern"
  },
  {
    "blockId": 15723,
    "page": 524,
    "text": "Exercise 15.11",
    "normalizedTitle": "Exercise 15.11",
    "level": 3,
    "confidence": 0.8300000000000001,
    "source": "pattern"
  },
  {
    "blockId": 15828,
    "page": 529,
    "text": "Exercise 15.12",
    "normalizedTitle": "Exercise 15.12",
    "level": 3,
    "confidence": 0.8300000000000001,
    "source": "pattern"
  },
  {
    "blockId": 15854,
    "page": 530,
    "text": "15.8 Area of a triangle",
    "normalizedTitle": "15.8 Area of a triangle",
    "level": 2,
    "confidence": 0.88,
    "source": "pattern"
  },
  {
    "blockId": 15887,
    "page": 532,
    "text": "Exercise 15.13",
    "normalizedTitle": "Exercise 15.13",
    "level": 3,
    "confidence": 0.8300000000000001,
    "source": "pattern"
  },
  {
    "blockId": 15915,
    "page": 534,
    "text": "15.9 Trigonometry in three dimensions",
    "normalizedTitle": "15.9 Trigonometry in three dimensions",
    "level": 2,
    "confidence": 0.88,
    "source": "pattern"
  },
  {
    "blockId": 15948,
    "page": 536,
    "text": "Exercise 15.14",
    "normalizedTitle": "Exercise 15.14",
    "level": 3,
    "confidence": 0.8300000000000001,
    "source": "pattern"
  },
  {
    "blockId": 16100,
    "page": 543,
    "text": "16.1 Introduction to bivariate data",
    "normalizedTitle": "16.1 Introduction to bivariate data",
    "level": 2,
    "confidence": 0.88,
    "source": "pattern"
  },
  {
    "blockId": 16178,
    "page": 548,
    "text": "Exercise 16.1",
    "normalizedTitle": "Exercise 16.1",
    "level": 3,
    "confidence": 0.8300000000000001,
    "source": "pattern"
  },
  {
    "blockId": 16417,
    "page": 562,
    "text": "Chapter 17",
    "normalizedTitle": "Chapter 17",
    "level": 1,
    "confidence": 0.98,
    "source": "pattern"
  },
  {
    "blockId": 16462,
    "page": 564,
    "text": "17.1 Earning money",
    "normalizedTitle": "17.1 Earning money",
    "level": 2,
    "confidence": 0.88,
    "source": "pattern"
  },
  {
    "blockId": 16497,
    "page": 565,
    "text": "Exercise 17.1",
    "normalizedTitle": "Exercise 17.1",
    "level": 3,
    "confidence": 0.8300000000000001,
    "source": "pattern"
  },
  {
    "blockId": 16524,
    "page": 566,
    "text": "Exercise 17.2",
    "normalizedTitle": "Exercise 17.2",
    "level": 3,
    "confidence": 0.8300000000000001,
    "source": "pattern"
  },
  {
    "blockId": 16586,
    "page": 569,
    "text": "Exercise 17.3",
    "normalizedTitle": "Exercise 17.3",
    "level": 3,
    "confidence": 0.8300000000000001,
    "source": "pattern"
  },
  {
    "blockId": 16611,
    "page": 569,
    "text": "17.2 Borrowing and investing money",
    "normalizedTitle": "17.2 Borrowing and investing money",
    "level": 2,
    "confidence": 0.88,
    "source": "pattern"
  },
  {
    "blockId": 16659,
    "page": 572,
    "text": "Exercise 17.4",
    "normalizedTitle": "Exercise 17.4",
    "level": 3,
    "confidence": 0.8300000000000001,
    "source": "pattern"
  },
  {
    "blockId": 16721,
    "page": 574,
    "text": "Exercise 17.5",
    "normalizedTitle": "Exercise 17.5",
    "level": 3,
    "confidence": 0.8300000000000001,
    "source": "pattern"
  },
  {
    "blockId": 16811,
    "page": 578,
    "text": "Exercise 17.6",
    "normalizedTitle": "Exercise 17.6",
    "level": 3,
    "confidence": 0.8300000000000001,
    "source": "pattern"
  },
  {
    "blockId": 16862,
    "page": 580,
    "text": "Exercise 17.7",
    "normalizedTitle": "Exercise 17.7",
    "level": 3,
    "confidence": 0.8300000000000001,
    "source": "pattern"
  },
  {
    "blockId": 16904,
    "page": 582,
    "text": "17.3 Buying and selling",
    "normalizedTitle": "17.3 Buying and selling",
    "level": 2,
    "confidence": 0.88,
    "source": "pattern"
  },
  {
    "blockId": 16941,
    "page": 584,
    "text": "Exercise 17.9",
    "normalizedTitle": "Exercise 17.9",
    "level": 3,
    "confidence": 0.8300000000000001,
    "source": "pattern"
  },
  {
    "blockId": 16970,
    "page": 585,
    "text": "Exercise 17.10",
    "normalizedTitle": "Exercise 17.10",
    "level": 3,
    "confidence": 0.8300000000000001,
    "source": "pattern"
  },
  {
    "blockId": 17065,
    "page": 590,
    "text": "Chapter 18",
    "normalizedTitle": "Chapter 18",
    "level": 1,
    "confidence": 0.98,
    "source": "pattern"
  },
  {
    "blockId": 17113,
    "page": 593,
    "text": "18.1 Review of quadratic graphs (the parabola)",
    "normalizedTitle": "18.1 Review of quadratic graphs (the parabola)",
    "level": 2,
    "confidence": 0.88,
    "source": "pattern"
  },
  {
    "blockId": 17135,
    "page": 594,
    "text": "Exercise 18.1",
    "normalizedTitle": "Exercise 18.1",
    "level": 3,
    "confidence": 0.8300000000000001,
    "source": "pattern"
  },
  {
    "blockId": 17198,
    "page": 598,
    "text": "Exercise 18.2",
    "normalizedTitle": "Exercise 18.2",
    "level": 3,
    "confidence": 0.8300000000000001,
    "source": "pattern"
  },
  {
    "blockId": 17323,
    "page": 604,
    "text": "Exercise 18.3",
    "normalizedTitle": "Exercise 18.3",
    "level": 3,
    "confidence": 0.8300000000000001,
    "source": "pattern"
  },
  {
    "blockId": 17361,
    "page": 605,
    "text": "18.2 Drawing reciprocal graphs (the hyperbola)",
    "normalizedTitle": "18.2 Drawing reciprocal graphs (the hyperbola)",
    "level": 2,
    "confidence": 0.88,
    "source": "pattern"
  },
  {
    "blockId": 17435,
    "page": 609,
    "text": "Exercise 18.4",
    "normalizedTitle": "Exercise 18.4",
    "level": 3,
    "confidence": 0.8300000000000001,
    "source": "pattern"
  },
  {
    "blockId": 17481,
    "page": 611,
    "text": "18.3 Using graphs to solve quadratic equations",
    "normalizedTitle": "18.3 Using graphs to solve quadratic equations",
    "level": 2,
    "confidence": 0.88,
    "source": "pattern"
  },
  {
    "blockId": 17516,
    "page": 612,
    "text": "Exercise 18.5",
    "normalizedTitle": "Exercise 18.5",
    "level": 3,
    "confidence": 0.8300000000000001,
    "source": "pattern"
  },
  {
    "blockId": 17550,
    "page": 614,
    "text": "18.4 Simultaneous linear and non-linear equations",
    "normalizedTitle": "18.4 Simultaneous linear and non-linear equations",
    "level": 2,
    "confidence": 0.88,
    "source": "pattern"
  },
  {
    "blockId": 17606,
    "page": 616,
    "text": "Exercise 18.6",
    "normalizedTitle": "Exercise 18.6",
    "level": 3,
    "confidence": 0.8300000000000001,
    "source": "pattern"
  },
  {
    "blockId": 17631,
    "page": 617,
    "text": "18.5 Other non-linear graphs",
    "normalizedTitle": "18.5 Other non-linear graphs",
    "level": 2,
    "confidence": 0.88,
    "source": "pattern"
  },
  {
    "blockId": 17690,
    "page": 620,
    "text": "Exercise 18.7",
    "normalizedTitle": "Exercise 18.7",
    "level": 3,
    "confidence": 0.8300000000000001,
    "source": "pattern"
  },
  {
    "blockId": 17753,
    "page": 623,
    "text": "Exercise 18.8",
    "normalizedTitle": "Exercise 18.8",
    "level": 3,
    "confidence": 0.8300000000000001,
    "source": "pattern"
  },
  {
    "blockId": 17786,
    "page": 625,
    "text": "Exercise 18.9",
    "normalizedTitle": "Exercise 18.9",
    "level": 3,
    "confidence": 0.8300000000000001,
    "source": "pattern"
  },
  {
    "blockId": 17834,
    "page": 628,
    "text": "18.6 Finding the gradient of a curve",
    "normalizedTitle": "18.6 Finding the gradient of a curve",
    "level": 2,
    "confidence": 0.88,
    "source": "pattern"
  },
  {
    "blockId": 17881,
    "page": 631,
    "text": "Exercise 18.10",
    "normalizedTitle": "Exercise 18.10",
    "level": 3,
    "confidence": 0.8300000000000001,
    "source": "pattern"
  },
  {
    "blockId": 17894,
    "page": 632,
    "text": "18.7 Derivatives of functions",
    "normalizedTitle": "18.7 Derivatives of functions",
    "level": 2,
    "confidence": 0.88,
    "source": "pattern"
  },
  {
    "blockId": 17950,
    "page": 634,
    "text": "Exercise 18.11",
    "normalizedTitle": "Exercise 18.11",
    "level": 3,
    "confidence": 0.8300000000000001,
    "source": "pattern"
  },
  {
    "blockId": 17993,
    "page": 635,
    "text": "Exercise 18.12",
    "normalizedTitle": "Exercise 18.12",
    "level": 3,
    "confidence": 0.8300000000000001,
    "source": "pattern"
  },
  {
    "blockId": 18037,
    "page": 636,
    "text": "Exercise 18.13",
    "normalizedTitle": "Exercise 18.13",
    "level": 3,
    "confidence": 0.8300000000000001,
    "source": "pattern"
  },
  {
    "blockId": 18100,
    "page": 638,
    "text": "Exercise 18.14",
    "normalizedTitle": "Exercise 18.14",
    "level": 3,
    "confidence": 0.8300000000000001,
    "source": "pattern"
  },
  {
    "blockId": 18189,
    "page": 643,
    "text": "Exercise 18.15",
    "normalizedTitle": "Exercise 18.15",
    "level": 3,
    "confidence": 0.8300000000000001,
    "source": "pattern"
  },
  {
    "blockId": 18338,
    "page": 649,
    "text": "Chapter 19",
    "normalizedTitle": "Chapter 19",
    "level": 1,
    "confidence": 0.98,
    "source": "pattern"
  },
  {
    "blockId": 18372,
    "page": 651,
    "text": "19.1 Symmetry in two dimensions",
    "normalizedTitle": "19.1 Symmetry in two dimensions",
    "level": 2,
    "confidence": 0.88,
    "source": "pattern"
  },
  {
    "blockId": 18395,
    "page": 652,
    "text": "Exercise 19.1",
    "normalizedTitle": "Exercise 19.1",
    "level": 3,
    "confidence": 0.8300000000000001,
    "source": "pattern"
  },
  {
    "blockId": 18455,
    "page": 655,
    "text": "Exercise 19.2",
    "normalizedTitle": "Exercise 19.2",
    "level": 3,
    "confidence": 0.8300000000000001,
    "source": "pattern"
  },
  {
    "blockId": 18511,
    "page": 657,
    "text": "19.2 Symmetry in three dimensions",
    "normalizedTitle": "19.2 Symmetry in three dimensions",
    "level": 2,
    "confidence": 0.88,
    "source": "pattern"
  },
  {
    "blockId": 18525,
    "page": 657,
    "text": "Exercise 19.3",
    "normalizedTitle": "Exercise 19.3",
    "level": 3,
    "confidence": 0.8300000000000001,
    "source": "pattern"
  },
  {
    "blockId": 18547,
    "page": 659,
    "text": "Exercise 19.4",
    "normalizedTitle": "Exercise 19.4",
    "level": 3,
    "confidence": 0.8300000000000001,
    "source": "pattern"
  },
  {
    "blockId": 18560,
    "page": 659,
    "text": "19.3 Symmetry properties of circles",
    "normalizedTitle": "19.3 Symmetry properties of circles",
    "level": 2,
    "confidence": 0.88,
    "source": "pattern"
  },
  {
    "blockId": 18631,
    "page": 662,
    "text": "Exercise 19.5",
    "normalizedTitle": "Exercise 19.5",
    "level": 3,
    "confidence": 0.8300000000000001,
    "source": "pattern"
  },
  {
    "blockId": 18657,
    "page": 664,
    "text": "19.4 Angle relationships in circles",
    "normalizedTitle": "19.4 Angle relationships in circles",
    "level": 2,
    "confidence": 0.88,
    "source": "pattern"
  },
  {
    "blockId": 18681,
    "page": 665,
    "text": "Exercise 19.6",
    "normalizedTitle": "Exercise 19.6",
    "level": 3,
    "confidence": 0.8300000000000001,
    "source": "pattern"
  },
  {
    "blockId": 18739,
    "page": 668,
    "text": "Exercise 19.7",
    "normalizedTitle": "Exercise 19.7",
    "level": 3,
    "confidence": 0.8300000000000001,
    "source": "pattern"
  },
  {
    "blockId": 18822,
    "page": 673,
    "text": "Exercise 19.8",
    "normalizedTitle": "Exercise 19.8",
    "level": 3,
    "confidence": 0.8300000000000001,
    "source": "pattern"
  },
  {
    "blockId": 18962,
    "page": 681,
    "text": "20.1 Histograms",
    "normalizedTitle": "20.1 Histograms",
    "level": 2,
    "confidence": 0.88,
    "source": "pattern"
  },
  {
    "blockId": 19011,
    "page": 684,
    "text": "Exercise 20.1",
    "normalizedTitle": "Exercise 20.1",
    "level": 3,
    "confidence": 0.8300000000000001,
    "source": "pattern"
  },
  {
    "blockId": 19116,
    "page": 688,
    "text": "20.2 Cumulative frequency",
    "normalizedTitle": "20.2 Cumulative frequency",
    "level": 2,
    "confidence": 0.88,
    "source": "pattern"
  },
  {
    "blockId": 19242,
    "page": 694,
    "text": "Exercise 20.2",
    "normalizedTitle": "Exercise 20.2",
    "level": 3,
    "confidence": 0.8300000000000001,
    "source": "pattern"
  },
  {
    "blockId": 19280,
    "page": 695,
    "text": "Chapter 12. Instead, you use:  $\\frac{n}{4}, \\frac{n}{2}$  and  $\\frac{3n}{4}$ .",
    "normalizedTitle": "Chapter 12. Instead, you use:  $\\frac{n}{4}, \\frac{n}{2}$  and  $\\frac{3n}{4}$ .",
    "level": 1,
    "confidence": 0.95,
    "source": "pattern"
  },
  {
    "blockId": 19337,
    "page": 698,
    "text": "Exercise 20.3",
    "normalizedTitle": "Exercise 20.3",
    "level": 3,
    "confidence": 0.8300000000000001,
    "source": "pattern"
  },
  {
    "blockId": 19679,
    "page": 716,
    "text": "Unit 5 Project",
    "normalizedTitle": "Unit 5 Project",
    "level": 1,
    "confidence": 0.98,
    "source": "pattern"
  },
  {
    "blockId": 19756,
    "page": 720,
    "text": "21.1 Working with ratio",
    "normalizedTitle": "21.1 Working with ratio",
    "level": 2,
    "confidence": 0.88,
    "source": "pattern"
  },
  {
    "blockId": 19796,
    "page": 721,
    "text": "Exercise 21.1",
    "normalizedTitle": "Exercise 21.1",
    "level": 3,
    "confidence": 0.8300000000000001,
    "source": "pattern"
  },
  {
    "blockId": 19896,
    "page": 725,
    "text": "Exercise 21.2",
    "normalizedTitle": "Exercise 21.2",
    "level": 3,
    "confidence": 0.8300000000000001,
    "source": "pattern"
  },
  {
    "blockId": 19951,
    "page": 727,
    "text": "Exercise 21.3",
    "normalizedTitle": "Exercise 21.3",
    "level": 3,
    "confidence": 0.8300000000000001,
    "source": "pattern"
  },
  {
    "blockId": 19983,
    "page": 728,
    "text": "21.2 Ratio and scale",
    "normalizedTitle": "21.2 Ratio and scale",
    "level": 2,
    "confidence": 0.88,
    "source": "pattern"
  },
  {
    "blockId": 20067,
    "page": 730,
    "text": "Exercise 21.4",
    "normalizedTitle": "Exercise 21.4",
    "level": 3,
    "confidence": 0.8300000000000001,
    "source": "pattern"
  },
  {
    "blockId": 20129,
    "page": 733,
    "text": "21.3 Rates",
    "normalizedTitle": "21.3 Rates",
    "level": 2,
    "confidence": 0.88,
    "source": "pattern"
  },
  {
    "blockId": 20194,
    "page": 736,
    "text": "Exercise 21.5",
    "normalizedTitle": "Exercise 21.5",
    "level": 3,
    "confidence": 0.8300000000000001,
    "source": "pattern"
  },
  {
    "blockId": 20229,
    "page": 737,
    "text": "21.4 Kinematic graphs",
    "normalizedTitle": "21.4 Kinematic graphs",
    "level": 2,
    "confidence": 0.88,
    "source": "pattern"
  },
  {
    "blockId": 20258,
    "page": 738,
    "text": "Exercise 21.6",
    "normalizedTitle": "Exercise 21.6",
    "level": 3,
    "confidence": 0.8300000000000001,
    "source": "pattern"
  },
  {
    "blockId": 20320,
    "page": 741,
    "text": "Exercise 21.7",
    "normalizedTitle": "Exercise 21.7",
    "level": 3,
    "confidence": 0.8300000000000001,
    "source": "pattern"
  },
  {
    "blockId": 20422,
    "page": 746,
    "text": "Exercise 21.8",
    "normalizedTitle": "Exercise 21.8",
    "level": 3,
    "confidence": 0.8300000000000001,
    "source": "pattern"
  },
  {
    "blockId": 20446,
    "page": 747,
    "text": "21.5 Proportion",
    "normalizedTitle": "21.5 Proportion",
    "level": 2,
    "confidence": 0.88,
    "source": "pattern"
  },
  {
    "blockId": 20469,
    "page": 749,
    "text": "Exercise 21.9",
    "normalizedTitle": "Exercise 21.9",
    "level": 3,
    "confidence": 0.8300000000000001,
    "source": "pattern"
  },
  {
    "blockId": 20501,
    "page": 750,
    "text": "Exercise 21.10",
    "normalizedTitle": "Exercise 21.10",
    "level": 3,
    "confidence": 0.8300000000000001,
    "source": "pattern"
  },
  {
    "blockId": 20562,
    "page": 752,
    "text": "Exercise 21.11",
    "normalizedTitle": "Exercise 21.11",
    "level": 3,
    "confidence": 0.8300000000000001,
    "source": "pattern"
  },
  {
    "blockId": 20578,
    "page": 753,
    "text": "21.6 Direct and inverse proportion in algebraic terms",
    "normalizedTitle": "21.6 Direct and inverse proportion in algebraic terms",
    "level": 2,
    "confidence": 0.88,
    "source": "pattern"
  },
  {
    "blockId": 20648,
    "page": 755,
    "text": "Exercise 21.12",
    "normalizedTitle": "Exercise 21.12",
    "level": 3,
    "confidence": 0.8300000000000001,
    "source": "pattern"
  },
  {
    "blockId": 20794,
    "page": 762,
    "text": "Chapter 22",
    "normalizedTitle": "Chapter 22",
    "level": 1,
    "confidence": 0.98,
    "source": "pattern"
  },
  {
    "blockId": 20826,
    "page": 764,
    "text": "22.1 Setting up equations to solve problems",
    "normalizedTitle": "22.1 Setting up equations to solve problems",
    "level": 2,
    "confidence": 0.88,
    "source": "pattern"
  },
  {
    "blockId": 20831,
    "page": 764,
    "text": "Exercise 22.1",
    "normalizedTitle": "Exercise 22.1",
    "level": 3,
    "confidence": 0.8300000000000001,
    "source": "pattern"
  },
  {
    "blockId": 20913,
    "page": 767,
    "text": "Exercise 22.2",
    "normalizedTitle": "Exercise 22.2",
    "level": 3,
    "confidence": 0.8300000000000001,
    "source": "pattern"
  },
  {
    "blockId": 20947,
    "page": 768,
    "text": "Chapter 2 if you need some ideas for completing a 3:2:1 self assessment.",
    "normalizedTitle": "Chapter 2 if you need some ideas for completing a 3:2:1 self assessment.",
    "level": 1,
    "confidence": 0.95,
    "source": "pattern"
  },
  {
    "blockId": 20978,
    "page": 770,
    "text": "Exercise 22.3",
    "normalizedTitle": "Exercise 22.3",
    "level": 3,
    "confidence": 0.8300000000000001,
    "source": "pattern"
  },
  {
    "blockId": 21010,
    "page": 771,
    "text": "22.2 Using and rearranging formulae",
    "normalizedTitle": "22.2 Using and rearranging formulae",
    "level": 2,
    "confidence": 0.88,
    "source": "pattern"
  },
  {
    "blockId": 21056,
    "page": 773,
    "text": "Exercise 22.4",
    "normalizedTitle": "Exercise 22.4",
    "level": 3,
    "confidence": 0.8300000000000001,
    "source": "pattern"
  },
  {
    "blockId": 21126,
    "page": 774,
    "text": "Exercise 22.5",
    "normalizedTitle": "Exercise 22.5",
    "level": 3,
    "confidence": 0.8300000000000001,
    "source": "pattern"
  },
  {
    "blockId": 21164,
    "page": 776,
    "text": "22.3 Functions and function notation",
    "normalizedTitle": "22.3 Functions and function notation",
    "level": 2,
    "confidence": 0.88,
    "source": "pattern"
  },
  {
    "blockId": 21279,
    "page": 780,
    "text": "Exercise 22.6",
    "normalizedTitle": "Exercise 22.6",
    "level": 3,
    "confidence": 0.8300000000000001,
    "source": "pattern"
  },
  {
    "blockId": 21381,
    "page": 783,
    "text": "Exercise 22.7",
    "normalizedTitle": "Exercise 22.7",
    "level": 3,
    "confidence": 0.8300000000000001,
    "source": "pattern"
  },
  {
    "blockId": 21477,
    "page": 785,
    "text": "Exercise 22.8",
    "normalizedTitle": "Exercise 22.8",
    "level": 3,
    "confidence": 0.8300000000000001,
    "source": "pattern"
  },
  {
    "blockId": 21599,
    "page": 789,
    "text": "Chapter 23",
    "normalizedTitle": "Chapter 23",
    "level": 1,
    "confidence": 0.98,
    "source": "pattern"
  },
  {
    "blockId": 21649,
    "page": 791,
    "text": "23.1 Simple plane transformations",
    "normalizedTitle": "23.1 Simple plane transformations",
    "level": 2,
    "confidence": 0.88,
    "source": "pattern"
  },
  {
    "blockId": 21722,
    "page": 794,
    "text": "Exercise 23.1",
    "normalizedTitle": "Exercise 23.1",
    "level": 3,
    "confidence": 0.8300000000000001,
    "source": "pattern"
  },
  {
    "blockId": 21786,
    "page": 798,
    "text": "Exercise 23.2",
    "normalizedTitle": "Exercise 23.2",
    "level": 3,
    "confidence": 0.8300000000000001,
    "source": "pattern"
  },
  {
    "blockId": 21837,
    "page": 801,
    "text": "Exercise 23.3",
    "normalizedTitle": "Exercise 23.3",
    "level": 3,
    "confidence": 0.8300000000000001,
    "source": "pattern"
  },
  {
    "blockId": 21929,
    "page": 805,
    "text": "Exercise 23.4",
    "normalizedTitle": "Exercise 23.4",
    "level": 3,
    "confidence": 0.8300000000000001,
    "source": "pattern"
  },
  {
    "blockId": 21966,
    "page": 809,
    "text": "23.2 Further transformations",
    "normalizedTitle": "23.2 Further transformations",
    "level": 2,
    "confidence": 0.88,
    "source": "pattern"
  },
  {
    "blockId": 22021,
    "page": 813,
    "text": "Exercise 23.5",
    "normalizedTitle": "Exercise 23.5",
    "level": 3,
    "confidence": 0.8300000000000001,
    "source": "pattern"
  },
  {
    "blockId": 22053,
    "page": 817,
    "text": "23.3 Vectors",
    "normalizedTitle": "23.3 Vectors",
    "level": 2,
    "confidence": 0.88,
    "source": "pattern"
  },
  {
    "blockId": 22091,
    "page": 820,
    "text": "Exercise 23.6",
    "normalizedTitle": "Exercise 23.6",
    "level": 3,
    "confidence": 0.8300000000000001,
    "source": "pattern"
  },
  {
    "blockId": 22152,
    "page": 823,
    "text": "Exercise 23.7",
    "normalizedTitle": "Exercise 23.7",
    "level": 3,
    "confidence": 0.8300000000000001,
    "source": "pattern"
  },
  {
    "blockId": 22259,
    "page": 828,
    "text": "Exercise 23.8",
    "normalizedTitle": "Exercise 23.8",
    "level": 3,
    "confidence": 0.8300000000000001,
    "source": "pattern"
  },
  {
    "blockId": 22357,
    "page": 831,
    "text": "Exercise 23.9",
    "normalizedTitle": "Exercise 23.9",
    "level": 3,
    "confidence": 0.8300000000000001,
    "source": "pattern"
  },
  {
    "blockId": 22511,
    "page": 838,
    "text": "Chapter 24",
    "normalizedTitle": "Chapter 24",
    "level": 1,
    "confidence": 0.98,
    "source": "pattern"
  },
  {
    "blockId": 22534,
    "page": 840,
    "text": "24.1 Using tree diagrams to show",
    "normalizedTitle": "24.1 Using tree diagrams to show",
    "level": 2,
    "confidence": 0.88,
    "source": "pattern"
  },
  {
    "blockId": 22553,
    "page": 841,
    "text": "Exercise 24.1",
    "normalizedTitle": "Exercise 24.1",
    "level": 3,
    "confidence": 0.8300000000000001,
    "source": "pattern"
  },
  {
    "blockId": 22564,
    "page": 841,
    "text": "24.2 Calculating probability from tree diagrams",
    "normalizedTitle": "24.2 Calculating probability from tree diagrams",
    "level": 2,
    "confidence": 0.88,
    "source": "pattern"
  },
  {
    "blockId": 22617,
    "page": 843,
    "text": "Exercise 24.2",
    "normalizedTitle": "Exercise 24.2",
    "level": 3,
    "confidence": 0.8300000000000001,
    "source": "pattern"
  },
  {
    "blockId": 22674,
    "page": 845,
    "text": "24.3 Calculating probability from Venn diagrams",
    "normalizedTitle": "24.3 Calculating probability from Venn diagrams",
    "level": 2,
    "confidence": 0.88,
    "source": "pattern"
  },
  {
    "blockId": 22731,
    "page": 848,
    "text": "Exercise 24.3",
    "normalizedTitle": "Exercise 24.3",
    "level": 3,
    "confidence": 0.8300000000000001,
    "source": "pattern"
  },
  {
    "blockId": 22809,
    "page": 851,
    "text": "24.4 Conditional probability",
    "normalizedTitle": "24.4 Conditional probability",
    "level": 2,
    "confidence": 0.88,
    "source": "pattern"
  },
  {
    "blockId": 22908,
    "page": 854,
    "text": "Exercise 24.4",
    "normalizedTitle": "Exercise 24.4",
    "level": 3,
    "confidence": 0.8300000000000001,
    "source": "pattern"
  }
]